fider_py-0.0.5.dist-info/licenses/AUTHORS
fider_py-0.0.5.dist-info/licenses/LICENSE
fiderpy/__init__.py
fiderpy/fider.py
fiderpy/py.typed
fiderpy/v1/__init__.py
fiderpy/v1/resources/__init__.py
fiderpy/v1/resources/comments/__init__.py
fiderpy/v1/resources/comments/adapters.py
fiderpy/v1/resources/comments/client.py
fiderpy/v1/resources/comments/request.py
fiderpy/v1/resources/comments/response.py
fiderpy/v1/resources/comments/service.py
fiderpy/v1/resources/posts/__init__.py
fiderpy/v1/resources/posts/adapters.py
fiderpy/v1/resources/posts/client.py
fiderpy/v1/resources/posts/enums.py
fiderpy/v1/resources/posts/request.py
fiderpy/v1/resources/posts/response.py
fiderpy/v1/resources/posts/service.py
fiderpy/v1/resources/tags/__init__.py
fiderpy/v1/resources/tags/adapters.py
fiderpy/v1/resources/tags/client.py
fiderpy/v1/resources/tags/request.py
fiderpy/v1/resources/tags/response.py
fiderpy/v1/resources/tags/service.py
fiderpy/v1/resources/users/__init__.py
fiderpy/v1/resources/users/adapters.py
fiderpy/v1/resources/users/client.py
fiderpy/v1/resources/users/request.py
fiderpy/v1/resources/users/response.py
fiderpy/v1/resources/users/service.py
fiderpy/v1/resources/votes/__init__.py
fiderpy/v1/resources/votes/adapters.py
fiderpy/v1/resources/votes/client.py
fiderpy/v1/resources/votes/request.py
fiderpy/v1/resources/votes/response.py
fiderpy/v1/resources/votes/service.py
fiderpy/v1/utils/__init__.py
fiderpy/v1/utils/adapters.py
fiderpy/v1/utils/decorators.py
fiderpy/v1/utils/domain.py
fiderpy/v1/utils/enums.py
fiderpy/v1/utils/exceptions.py
fiderpy/v1/utils/http.py
fiderpy/v1/utils/interfaces.py
fiderpy/v1/utils/types.py
fider_py-0.0.5.dist-info/METADATA
fider_py-0.0.5.dist-info/WHEEL
fider_py-0.0.5.dist-info/top_level.txt
fider_py-0.0.5.dist-info/RECORD
