Metadata-Version: 2.4
Name: fider-py
Version: 0.0.5
Summary: Python SDK for Fider.io v1 api
Maintainer-email: Nick Kelly <nialexanderke@proton.me>
Project-URL: Homepage, https://github.com/nickatnight/fider-py
Project-URL: Issues, https://github.com/nickatnight/fider-py/issues
Classifier: Development Status :: 4 - Beta
Classifier: Intended Audience :: Developers
Classifier: License :: OSI Approved :: MIT License
Classifier: Programming Language :: Python :: 3
Classifier: Programming Language :: Python :: 3.10
Classifier: Programming Language :: Python :: 3.11
Classifier: Programming Language :: Python :: 3.12
Classifier: Programming Language :: Python :: 3.13
Classifier: Topic :: Software Development :: Libraries :: Python Modules
Classifier: Typing :: Typed
Requires-Python: >=3.10
License-File: LICENSE
License-File: AUTHORS
Requires-Dist: requests==2.32.4
Dynamic: license-file
